request_catcher/__init__.py
request_catcher/db.py
request_catcher/decorator.py
catchttp-1.0.0.dist-info/LICENSE
catchttp-1.0.0.dist-info/METADATA
catchttp-1.0.0.dist-info/WHEEL
catchttp-1.0.0.dist-info/top_level.txt
catchttp-1.0.0.dist-info/RECORD
